chaosmesh/__init__.py
chaosmesh/client.py
chaosmesh/experiments/__init__.py
chaosmesh/experiments/factory.py
chaosmesh/experiments/base/__init__.py
chaosmesh/experiments/base/hosts/__init__.py
chaosmesh/experiments/base/hosts/disk/__init__.py
chaosmesh/experiments/base/hosts/disk/fill.py
chaosmesh/experiments/base/hosts/disk/read_payload.py
chaosmesh/experiments/base/hosts/disk/write_payload.py
chaosmesh/experiments/base/hosts/networkattack/__init__.py
chaosmesh/experiments/base/hosts/stress/__init__.py
chaosmesh/experiments/base/hosts/stress/cpu.py
chaosmesh/experiments/base/hosts/stress/memory.py
chaosmesh/experiments/base/k8s/__init__.py
chaosmesh/experiments/base/k8s/jvmfault/__init__.py
chaosmesh/experiments/base/k8s/jvmfault/gc.py
chaosmesh/experiments/base/k8s/jvmfault/raise_exception.py
chaosmesh/experiments/base/k8s/network/__init__.py
chaosmesh/experiments/base/k8s/network/bandwidth.py
chaosmesh/experiments/base/k8s/network/partition.py
chaosmesh/experiments/base/k8s/podfault/__init__.py
chaosmesh/experiments/base/k8s/podfault/container_kill.py
chaosmesh/experiments/base/k8s/podfault/pod_failure.py
chaosmesh/experiments/base/k8s/podfault/pod_kill.py
chaosmesh/experiments/base/k8s/stress/__init__.py
chaosmesh/experiments/base/k8s/stress/cpu.py
chaosmesh/experiments/base/k8s/stress/memory.py
chaosmesh/experiments/v1alpha1/__init__.py
chaosmesh/experiments/v1alpha1/hosts/__init__.py
chaosmesh/experiments/v1alpha1/hosts/disk/__init__.py
chaosmesh/experiments/v1alpha1/hosts/disk/fill.py
chaosmesh/experiments/v1alpha1/hosts/disk/read_payload.py
chaosmesh/experiments/v1alpha1/hosts/disk/write_payload.py
chaosmesh/experiments/v1alpha1/hosts/networkattack/__init__.py
chaosmesh/experiments/v1alpha1/hosts/stress/__init__.py
chaosmesh/experiments/v1alpha1/hosts/stress/cpu.py
chaosmesh/experiments/v1alpha1/hosts/stress/memory.py
chaosmesh/experiments/v1alpha1/k8s/__init__.py
chaosmesh/experiments/v1alpha1/k8s/jvmfault/__init__.py
client_library_for_chaos_mesh-1.2.17.dist-info/METADATA
client_library_for_chaos_mesh-1.2.17.dist-info/WHEEL
client_library_for_chaos_mesh-1.2.17.dist-info/top_level.txt
client_library_for_chaos_mesh-1.2.17.dist-info/RECORD
