Metadata-Version: 2.1
Name: client-library-for-chaos-mesh
Version: 1.2.17
Summary: A client to create experiments in ChaosMesh
Home-page: https://github.com/vishrantgupta/client-library-for-chaos-mesh
Author: Vishrant Gupta
Author-email: vishrant.gupta@gmail.com
Requires-Dist: kubernetes >=21.7.0
Requires-Dist: polling >=0.3.2
